jessilver_django_seed/__init__.py
jessilver_django_seed/apps.py
jessilver_django_seed/__pycache__/__init__.cpython-312.pyc
jessilver_django_seed/__pycache__/apps.cpython-312.pyc
jessilver_django_seed/management/commands/seed.py
jessilver_django_seed/management/commands/seeder_creation.py
jessilver_django_seed/management/commands/seeder_utils.py
jessilver_django_seed/management/commands/__pycache__/seed.cpython-312.pyc
jessilver_django_seed/management/commands/__pycache__/seeder_creation.cpython-312.pyc
jessilver_django_seed/management/commands/__pycache__/seeder_utils.cpython-312.pyc
jessilver_django_seed/seeders/BaseSeeder.py
jessilver_django_seed/seeders/__init__.py
jessilver_django_seed/seeders/__pycache__/BaseSeeder.cpython-312.pyc
jessilver_django_seed/seeders/__pycache__/__init__.cpython-312.pyc
jessilver_django_seed-2.0.1.dist-info/licenses/LICENSE
jessilver_django_seed-2.0.1.dist-info/METADATA
jessilver_django_seed-2.0.1.dist-info/WHEEL
jessilver_django_seed-2.0.1.dist-info/top_level.txt
jessilver_django_seed-2.0.1.dist-info/RECORD
