Metadata-Version: 2.4
Name: jessilver_django_seed
Version: 2.0.1
Summary: A library to facilitate the creation of fake data (seeds) in Django projects.
Home-page: https://github.com/jessilver/django_seed
Author: Jesse Silva
Author-email: jesse1eliseu@gmail.com
License: MIT License
Project-URL: Documentation, https://github.com/jessilver/django_seed#readme
Project-URL: Source, https://github.com/jessilver/django_seed
Project-URL: Tracker, https://github.com/jessilver/django_seed/issues
Keywords: django,seed,fake data,testing,development
Classifier: Development Status :: 4 - Beta
Classifier: Intended Audience :: Developers
Classifier: License :: OSI Approved :: MIT License
Classifier: Programming Language :: Python :: 3
Classifier: Framework :: Django
Requires-Python: >=3.7
License-File: LICENSE
Requires-Dist: Django>=3.2
Requires-Dist: astor>=0.8.1
Dynamic: author
Dynamic: author-email
Dynamic: classifier
Dynamic: description
Dynamic: description-content-type
Dynamic: home-page
Dynamic: keywords
Dynamic: license
Dynamic: license-file
Dynamic: project-url
Dynamic: requires-dist
Dynamic: requires-python
Dynamic: summary
